starlette_views.py
starlette_views-0.0.4.dist-info/LICENSE
starlette_views-0.0.4.dist-info/METADATA
starlette_views-0.0.4.dist-info/WHEEL
starlette_views-0.0.4.dist-info/top_level.txt
starlette_views-0.0.4.dist-info/RECORD
