Metadata-Version: 2.1
Name: starlette-views
Version: 0.0.4
Summary: Create endpoints simpler
Home-page: UNKNOWN
Author: Kirill Klenov
Author-email: horneds@gmail.com
License: MIT
Keywords: starlette views
Platform: UNKNOWN
Classifier: Development Status :: 5 - Production/Stable
Classifier: Intended Audience :: Developers
Classifier: License :: OSI Approved :: MIT License
Classifier: Topic :: Software Development :: Libraries
Classifier: Programming Language :: Python :: 3.7
Classifier: Programming Language :: Python :: 3.8
